[
  {
    "anonymous": false,
    "inputs": [
      {
        "indexed": false,
        "internalType": "address",
        "name": "module",
        "type": "address"
      }
    ],
    "name": "ModuleDeRegistered",
    "type": "event"
  },
  {
    "anonymous": false,
    "inputs": [
      {
        "indexed": true,
        "internalType": "address",
        "name": "module",
        "type": "address"
      },
      {
        "indexed": false,
        "internalType": "bytes32",
        "name": "name",
        "type": "bytes32"
      }
    ],
    "name": "ModuleRegistered",
    "type": "event"
  },
  {
    "anonymous": false,
    "inputs": [
      {
        "indexed": true,
        "internalType": "address",
        "name": "_newOwner",
        "type": "address"
      }
    ],
    "name": "OwnerChanged",
    "type": "event"
  },
  {
    "anonymous": false,
    "inputs": [
      {
        "indexed": false,
        "internalType": "address",
        "name": "upgrader",
        "type": "address"
      }
    ],
    "name": "UpgraderDeRegistered",
    "type": "event"
  },
  {
    "anonymous": false,
    "inputs": [
      {
        "indexed": false,
        "internalType": "address",
        "name": "upgrader",
        "type": "address"
      },
      {
        "indexed": false,
        "internalType": "bytes32",
        "name": "name",
        "type": "bytes32"
      }
    ],
    "name": "UpgraderRegistered",
    "type": "event"
  },
  {
    "inputs": [
      {
        "internalType": "address",
        "name": "_newOwner",
        "type": "address"
      }
    ],
    "name": "changeOwner",
    "outputs": [],
    "stateMutability": "nonpayable",
    "type": "function"
  },
  {
    "inputs": [],
    "name": "owner",
    "outputs": [
      {
        "internalType": "address",
        "name": "",
        "type": "address"
      }
    ],
    "stateMutability": "view",
    "type": "function"
  },
  {
    "inputs": [
      {
        "internalType": "address",
        "name": "_module",
        "type": "address"
      },
      {
        "internalType": "bytes32",
        "name": "_name",
        "type": "bytes32"
      }
    ],
    "name": "registerModule",
    "outputs": [],
    "stateMutability": "nonpayable",
    "type": "function"
  },
  {
    "inputs": [
      {
        "internalType": "address",
        "name": "_module",
        "type": "address"
      }
    ],
    "name": "deregisterModule",
    "outputs": [],
    "stateMutability": "nonpayable",
    "type": "function"
  },
  {
    "inputs": [
      {
        "internalType": "address",
        "name": "_upgrader",
        "type": "address"
      },
      {
        "internalType": "bytes32",
        "name": "_name",
        "type": "bytes32"
      }
    ],
    "name": "registerUpgrader",
    "outputs": [],
    "stateMutability": "nonpayable",
    "type": "function"
  },
  {
    "inputs": [
      {
        "internalType": "address",
        "name": "_upgrader",
        "type": "address"
      }
    ],
    "name": "deregisterUpgrader",
    "outputs": [],
    "stateMutability": "nonpayable",
    "type": "function"
  },
  {
    "inputs": [
      {
        "internalType": "address",
        "name": "_token",
        "type": "address"
      }
    ],
    "name": "recoverToken",
    "outputs": [],
    "stateMutability": "nonpayable",
    "type": "function"
  },
  {
    "inputs": [
      {
        "internalType": "address",
        "name": "_module",
        "type": "address"
      }
    ],
    "name": "moduleInfo",
    "outputs": [
      {
        "internalType": "bytes32",
        "name": "",
        "type": "bytes32"
      }
    ],
    "stateMutability": "view",
    "type": "function"
  },
  {
    "inputs": [
      {
        "internalType": "address",
        "name": "_upgrader",
        "type": "address"
      }
    ],
    "name": "upgraderInfo",
    "outputs": [
      {
        "internalType": "bytes32",
        "name": "",
        "type": "bytes32"
      }
    ],
    "stateMutability": "view",
    "type": "function"
  },
  {
    "inputs": [
      {
        "internalType": "address",
        "name": "_module",
        "type": "address"
      }
    ],
    "name": "isRegisteredModule",
    "outputs": [
      {
        "internalType": "bool",
        "name": "",
        "type": "bool"
      }
    ],
    "stateMutability": "view",
    "type": "function"
  },
  {
    "inputs": [
      {
        "internalType": "address[]",
        "name": "_modules",
        "type": "address[]"
      }
    ],
    "name": "isRegisteredModule",
    "outputs": [
      {
        "internalType": "bool",
        "name": "",
        "type": "bool"
      }
    ],
    "stateMutability": "view",
    "type": "function"
  },
  {
    "inputs": [
      {
        "internalType": "address",
        "name": "_upgrader",
        "type": "address"
      }
    ],
    "name": "isRegisteredUpgrader",
    "outputs": [
      {
        "internalType": "bool",
        "name": "",
        "type": "bool"
      }
    ],
    "stateMutability": "view",
    "type": "function"
  }
]